MANIFEST.in
board_mydashboard_view.xml
board_view.xml
setup.py
./__init__.py
./__openerp__.py
./board.py
./controllers.py
i18n/ar.po
i18n/bg.po
i18n/board.pot
i18n/br.po
i18n/bs.po
i18n/ca.po
i18n/cs.po
i18n/da.po
i18n/de.po
i18n/el.po
i18n/en_GB.po
i18n/es.po
i18n/es_AR.po
i18n/es_CL.po
i18n/es_CR.po
i18n/es_EC.po
i18n/es_MX.po
i18n/es_PY.po
i18n/es_VE.po
i18n/et.po
i18n/fa.po
i18n/fi.po
i18n/fr.po
i18n/gl.po
i18n/gu.po
i18n/he.po
i18n/hr.po
i18n/hu.po
i18n/id.po
i18n/it.po
i18n/ja.po
i18n/ko.po
i18n/ln.po
i18n/lt.po
i18n/lv.po
i18n/mk.po
i18n/mn.po
i18n/nb.po
i18n/nl.po
i18n/nl_BE.po
i18n/pl.po
i18n/pt.po
i18n/pt_BR.po
i18n/ro.po
i18n/ru.po
i18n/sk.po
i18n/sl.po
i18n/sq.po
i18n/sr.po
i18n/sr@latin.po
i18n/sv.po
i18n/th.po
i18n/tlh.po
i18n/tr.po
i18n/uk.po
i18n/vi.po
i18n/zh_CN.po
i18n/zh_TW.po
images/1_dashboard_definition.jpeg
images/2_publish_note.jpeg
images/3_admin_dashboard.jpeg
openerp_board.egg-info/PKG-INFO
openerp_board.egg-info/SOURCES.txt
openerp_board.egg-info/dependency_links.txt
openerp_board.egg-info/requires.txt
openerp_board.egg-info/top_level.txt
security/ir.model.access.csv
static/src/img/layout_1-1-1.png
static/src/img/layout_1-1.png
static/src/img/layout_1-2.png
static/src/img/layout_1.png
static/src/img/layout_2-1.png
static/src/img/view_todo_arrow.png
static/src/js/dashboard.js
static/src/xml/board.xml